dfdb/__init__.py
dfdb/abc.py
dfdb/alter.py
dfdb/config.toml
dfdb/database.py
dfdb/dataframe.py
dfdb/defs.py
dfdb/parsing.py
dfdb/triggers.py
dfdb/types.py
dfdb-0.1.9.dist-info/LICENSE
dfdb-0.1.9.dist-info/METADATA
dfdb-0.1.9.dist-info/WHEEL
dfdb-0.1.9.dist-info/top_level.txt
dfdb-0.1.9.dist-info/RECORD
