Metadata-Version: 2.1
Name: dfdb
Version: 0.1.9
Summary: Pandas-like interface for manipulating SQL databases.
Author: Ho Yin Chau
License: MIT License
Project-URL: repository, https://github.com/hchau630/dfdb
Classifier: License :: OSI Approved :: MIT License
Classifier: Natural Language :: English
Classifier: Operating System :: OS Independent
Classifier: Programming Language :: Python :: 3.9
Requires-Python: >=3.9
License-File: LICENSE
Requires-Dist: numpy
Requires-Dist: pandas (>=1.5.3)
Requires-Dist: SQLAlchemy (>=2.0.0)
Requires-Dist: hyclib (>=0.1.13)
Requires-Dist: addict
Requires-Dist: beautifulsoup4
